{
    "nodes": [
        {"id": 1, "pids": [2], "name": "Adam", "gender": "male"},
        {"id": 2, "pids": [1], "name": "Eve", "gender": "female"},
        {"id": 3, "fid": 1, "mid": 2, "name": "Cain", "gender": "male"},
        {"id": 4, "fid": 1, "mid": 2, "name": "Abel", "gender": "male"},
        {"id": 5, "fid": 1, "mid": 2, "name": "Seth", "gender": "male"},
        {"id": 6, "fid": 3, "name": "Enoch", "gender": "male"},
        {"id": 7, "fid": 6, "name": "Lamech", "gender": "male"},
        {"id": 8, "fid": 5, "name": "Enosh", "gender": "male"},
        {"id": 9, "fid": 8, "name": "Kenan", "gender": "male"},
        {"id": 10, "fid": 9, "name": "Mahalalel", "gender": "male"},
        {"id": 11, "fid": 10, "name": "Jared", "gender": "male"},
        {"id": 12, "fid": 11, "name": "Enoch", "gender": "male"},
        {"id": 13, "fid": 12, "name": "Methuselah", "gender": "male"},
        {"id": 14, "fid": 13, "name": "Lamech", "gender": "male"},
        {"id": 15, "fid": 14, "name": "Noah", "gender": "male"},
        {"id": 16, "fid": 15, "name": "Shem", "gender": "male"},
        {"id": 17, "fid": 15, "name": "Ham", "gender": "male"},
        {"id": 19, "fid": 15, "name": "Japheth", "gender": "male"},
        {"id": 20, "fid": 19, "name": "Gomer", "gender": "male"},
        {"id": 21, "fid": 19, "name": "Magog", "gender": "male"},
        {"id": 22, "fid": 19, "name": "Madai", "gender": "male"},
        {"id": 23, "fid": 19, "name": "Javan", "gender": "male"},
        {"id": 24, "fid": 19, "name": "Tubal", "gender": "male"},
        {"id": 25, "fid": 19, "name": "Meshech", "gender": "male"},
        {"id": 26, "fid": 19, "name": "Tiras", "gender": "male"},
        {"id": 27, "fid": 20, "name": "Ashkenaz", "gender": "male"},
        {"id": 28, "fid": 20, "name": "Riphath", "gender": "male"},
        {"id": 29, "fid": 20, "name": "Togarmah", "gender": "male"},
        {"id": 30, "fid": 23, "name": "Elishah", "gender": "male"},
        {"id": 31, "fid": 23, "name": "Tarshish", "gender": "male"},
        {"id": 32, "fid": 23, "name": "Kittim", "gender": "male"},
        {"id": 33, "fid": 23, "name": "Dodanim", "alt_names": ["Rodanim"], "gender": "male"},
        {"id": 34, "fid": 17, "name": "Cush", "gender": "male"},
        {"id": 35, "fid": 17, "name": "Egypt", "alt_names": ["Pharaoh"], "gender": "male"},
        {"id": 36, "fid": 17, "name": "Put", "gender": "male"},
        {"id": 37, "fid": 17, "name": "Canaan", "alt_names": ["Canaanites"], "gender": "male"},
        {"id": 38, "fid": 17, "name": "Amalek", "alt_names": ["Amalekites"], "gender": "male"},
        {"id": 39, "fid": 16, "name": "Elam", "gender": "male"},
        {"id": 40, "fid": 34, "name": "Nimrod", "gender": "male"},
        {"id": 41, "fid": 40, "name": "Babylon", "alt_names": ["Babel"], "gender": "male"},
        {"id": 42, "fid": 41, "name": "Chaldeans", "gender": "male"},
        {"id": 43, "fid": 40, "name": "Nineveh", "alt_names": ["Assyria"], "gender": "male"},
        {"id": 44, "fid": 17, "name": "Caphtor", "alt_names": ["Caphtorim"], "gender": "male"},
        {"id": 45, "fid": 1, "name": "Nephilim", "gender": "male"},
        {"id": 46, "fid": 35, "name": "Ludim", "gender": "male"},
        {"id": 47, "fid": 35, "name": "Anamim", "gender": "male"},
        {"id": 48, "fid": 35, "name": "Lehabim", "gender": "male"},
        {"id": 49, "fid": 35, "name": "Naphtuhim", "gender": "male"},
        {"id": 50, "fid": 35, "name": "Pathrusim", "gender": "male"},
        {"id": 51, "fid": 35, "name": "Casluhim", "gender": "male"},
        {
            "id": 52,
            "fid": 51,
            "name": "Philistines",
            "alt_names": ["Abimelech (\"My Father is King\")"],
            "gender": "male"
        },
        {"id": 53, "fid": 52, "name": "Gaza", "gender": "male"},
        {"id": 54, "fid": 52, "name": "Ashdod", "gender": "male"},
        {"id": 55, "fid": 52, "name": "Ashkelon", "gender": "male"},
        {"id": 56, "fid": 52, "name": "Gath", "gender": "male"},
        {"id": 57, "fid": 52, "name": "Ekron", "gender": "male"},
        {"id": 58, "fid": 21, "name": "Gog", "gender": "male"},
        {"id": 59, "fid": 37, "name": "Lebanon", "alt_names": ["Phoenicia", "Phoenicians"], "gender": "male"},
        {"id": 60, "fid": 59, "name": "Sidon", "gender": "male"},
        {"id": 61, "fid": 59, "name": "Tyre", "gender": "male"},
        {"id": 62, "fid": 37, "name": "Heth", "alt_names": ["Hittites"], "gender": "male"},
        {"id": 63, "fid": 37, "name": "Jebusites", "gender": "male"},
        {"id": 64, "fid": 37, "name": "Amorites", "gender": "male"},
        {"id": 65, "fid": 37, "name": "Girgashites", "gender": "male"},
        {"id": 66, "fid": 37, "name": "Hivites", "gender": "male"},
        {"id": 67, "fid": 37, "name": "Perizzites", "gender": "male"},
        {"id": 68, "fid": 37, "name": "Rephaim", "gender": "male"},
        {"id": 69, "fid": 63, "name": "Adoni-zedek", "gender": "male"},
        {"id": 70, "fid": 64, "name": "Mamre", "gender": "male"},
        {"id": 71, "fid": 64, "name": "Sihon", "gender": "male"},
        {"id": 72, "fid": 66, "name": "Gibeon", "alt_names": ["Gibeonites"], "gender": "male"},
        {"id": 73, "fid": 68, "name": "Zamzummim", "alt_names": ["Zuzim"], "gender": "male"},
        {"id": 74, "fid": 68, "name": "Emim", "gender": "male"},
        {"id": 75, "fid": 68, "name": "Anak", "alt_names": ["Anakim"], "gender": "male"},
        {"id": 76, "fid": 68, "name": "Og", "gender": "male"},
        {"id": 77, "fid": 104, "name": "Shelah", "gender": "male"},
        {"id": 78, "fid": 77, "name": "Eber", "alt_names": ["Hebrew"], "gender": "male"},
        {"id": 79, "fid": 78, "name": "Peleg", "gender": "male"},
        {"id": 80, "fid": 79, "name": "Reu", "gender": "male"},
        {"id": 81, "fid": 80, "name": "Serug", "gender": "male"},
        {"id": 82, "fid": 81, "name": "Nahor", "gender": "male"},
        {"id": 83, "fid": 82, "name": "Terah", "gender": "male"},
        {"id": 84, "pids": [90, 91, 94], "fid": 83, "name": "Abraham", "alt_names": ["Abram"], "gender": "male"},
        {"id": 85, "pids": [122], "fid": 83, "name": "Nahor", "gender": "male"},
        {"id": 86, "fid": 83, "name": "Haran", "gender": "male"},
        {"id": 87, "fid": 86, "name": "Lot", "gender": "male"},
        {"id": 88, "fid": 87, "name": "Moab", "alt_names": ["Moabites"], "gender": "male"},
        {"id": 89, "fid": 87, "name": "Ben-ammi", "alt_names": ["Ammon", "Ammonites"], "gender": "male"},
        {"id": 90, "pids": [84], "name": "Sarah", "alt_names": ["Sarai"], "gender": "female"},
        {"id": 91, "pids": [84], "name": "Hagar", "gender": "female"},
        {"id": 92, "fid": 84, "mid": 91, "name": "Ishmael", "alt_names": ["Ishmaelites"], "gender": "male"},
        {"id": 93, "pids": [119], "fid": 84, "mid": 90, "name": "Isaac", "gender": "male"},
        {"id": 94, "pids": [84], "name": "Keturah", "gender": "female"},
        {"id": 95, "fid": 84, "mid": 94, "name": "Zimran", "gender": "male"},
        {"id": 96, "fid": 84, "mid": 94, "name": "Jokshan", "gender": "male"},
        {"id": 97, "fid": 84, "mid": 94, "name": "Medan", "gender": "male"},
        {"id": 98, "fid": 84, "mid": 94, "name": "Midian", "alt_names": ["Midianites", "Kenites"], "gender": "male"},
        {"id": 99, "fid": 84, "mid": 94, "name": "Ishbak", "gender": "male"},
        {"id": 100, "fid": 84, "mid": 94, "name": "Shuah", "gender": "male"},
        {"id": 101, "fid": 98, "name": "Jethro", "alt_names": ["Reuel", "Hobab"], "gender": "male"},
        {"id": 102, "fid": 101, "name": "Hobab", "gender": "male"},
        {"id": 103, "fid": 16, "name": "Asshur", "gender": "male"},
        {"id": 104, "fid": 16, "name": "Arpachshad", "gender": "male"},
        {"id": 105, "fid": 16, "name": "Lud", "gender": "male"},
        {"id": 106, "fid": 16, "name": "Aram", "gender": "male"},
        {"id": 107, "fid": 92, "name": "Nebaioth", "gender": "male"},
        {"id": 108, "fid": 92, "name": "Kedar", "gender": "male"},
        {"id": 109, "fid": 92, "name": "Abdeel", "gender": "male"},
        {"id": 110, "fid": 92, "name": "Mibsam", "gender": "male"},
        {"id": 111, "fid": 92, "name": "Mishma", "gender": "male"},
        {"id": 112, "fid": 92, "name": "Dumah", "gender": "male"},
        {"id": 113, "fid": 92, "name": "Messa", "gender": "male"},
        {"id": 114, "fid": 92, "name": "Hadad", "gender": "male"},
        {"id": 115, "fid": 92, "name": "Tema", "gender": "male"},
        {"id": 116, "fid": 92, "name": "Jetur", "gender": "male"},
        {"id": 117, "fid": 92, "name": "Naphish", "gender": "male"},
        {"id": 118, "fid": 92, "name": "Kedemah", "gender": "male"},
        {"id": 119, "pids": [93], "name": "Rebekah", "gender": "female"},
        {
            "id": 120,
            "fid": 93,
            "mid": 119,
            "name": "Esau",
            "alt_names": ["Edom", "Edomites", "Horites", "Seir"],
            "gender": "male"
        },
        {
            "id": 121,
            "pids": [125, 126, 133, 134],
            "fid": 93,
            "mid": 119,
            "name": "Jacob",
            "alt_names": ["Israel"],
            "gender": "male"
        },
        {"id": 122, "pids": [85], "name": "Milcah", "gender": "female"},
        {"id": 123, "fid": 85, "mid": 122, "name": "Bethuel", "gender": "male"},
        {"id": 124, "fid": 123, "name": "Laban", "gender": "male"},
        {"id": 125, "pids": [121], "name": "Leah", "gender": "female"},
        {"id": 126, "pids": [121], "name": "Rachel", "gender": "female"},
        {"id": 127, "fid": 121, "mid": 125, "name": "Reuben", "gender": "male"},
        {"id": 128, "fid": 121, "mid": 125, "name": "Simeon", "gender": "male"},
        {"id": 129, "fid": 121, "mid": 125, "name": "Levi", "gender": "male"},
        {"id": 130, "fid": 121, "mid": 125, "name": "Judah", "gender": "male"},
        {"id": 131, "fid": 121, "mid": 133, "name": "Dan", "gender": "male"},
        {"id": 132, "fid": 121, "mid": 133, "name": "Naphtali", "gender": "male"},
        {"id": 133, "pids": [121], "name": "Bilhah", "gender": "female"},
        {"id": 134, "pids": [121], "name": "Zilpah", "gender": "female"},
        {"id": 135, "fid": 121, "mid": 134, "name": "Gad", "gender": "male"},
        {"id": 137, "fid": 121, "mid": 134, "name": "Asher", "gender": "male"},
        {"id": 138, "fid": 121, "mid": 125, "name": "Issachar", "gender": "male"},
        {"id": 140, "fid": 121, "mid": 125, "name": "Zebulun", "gender": "male"},
        {"id": 141, "pids": [145], "fid": 121, "mid": 126, "name": "Joseph", "gender": "male"},
        {"id": 142, "fid": 121, "mid": 126, "name": "Benjamin", "gender": "male"},
        {"id": 143, "fid": 141, "mid": 145, "name": "Manasseh", "gender": "male"},
        {"id": 144, "fid": 141, "mid": 145, "name": "Ephraim", "gender": "male"},
        {"id": 145, "pids": [141], "name": "Asenath", "gender": "female"}
    ]
}
